perspective_ray_dashboard/__init__.py
perspective_ray_dashboard/demo.py
perspective_ray_dashboard/serve.py
perspective_ray_dashboard/static/index.js
perspective_ray_dashboard/tests/test_init.py
perspective_ray_dashboard-0.1.0.dist-info/METADATA
perspective_ray_dashboard-0.1.0.dist-info/WHEEL
perspective_ray_dashboard-0.1.0.dist-info/licenses/LICENSE
perspective_ray_dashboard-0.1.0.dist-info/RECORD
