Metadata-Version: 2.1
Name: perspective-ray-dashboard
Version: 0.1.0
Summary: A scalable ray dashboard built with perspective
Project-URL: repository, https://github.com/perspective-community/perspective-ray-dashboard
Project-URL: homepage, https://github.com/perspective-community/perspective-ray-dashboard
Author-email: Tim Paine <t.paine154@gmail.com>
License:                                  Apache License
License-File: LICENSE
Keywords: cluster,cluster visualization,data visualization,dataviz,perspective,ray
Classifier: Development Status :: 4 - Beta
Classifier: Framework :: Jupyter
Classifier: Framework :: Jupyter :: JupyterLab
Classifier: License :: OSI Approved :: Apache Software License
Classifier: Programming Language :: Python
Classifier: Programming Language :: Python :: 3
Classifier: Programming Language :: Python :: 3.7
Classifier: Programming Language :: Python :: 3.8
Classifier: Programming Language :: Python :: 3.9
Classifier: Programming Language :: Python :: 3.10
Classifier: Programming Language :: Python :: 3.11
Requires-Python: >=3.7
Requires-Dist: fastapi
Requires-Dist: perspective-python
Requires-Dist: pydantic<2
Requires-Dist: ray>=2.5
Provides-Extra: develop
Requires-Dist: black>=23; extra == 'develop'
Requires-Dist: bump2version>=1.0.0; extra == 'develop'
Requires-Dist: check-manifest; extra == 'develop'
Requires-Dist: pytest; extra == 'develop'
Requires-Dist: pytest-asyncio; extra == 'develop'
Requires-Dist: pytest-cov; extra == 'develop'
Requires-Dist: pytest-sugar; extra == 'develop'
Requires-Dist: ruff; extra == 'develop'
Provides-Extra: test
Requires-Dist: pytest; extra == 'test'
Requires-Dist: pytest-asyncio; extra == 'test'
Requires-Dist: pytest-cov; extra == 'test'
Requires-Dist: pytest-sugar; extra == 'test'
